barter_auth/__init__.py
barter_auth/auth.py
barter_auth/constants.py
barter_auth/exceptions.py
barter_auth/providers.py
barter_auth/settings.py
barter_auth/models/__init__.py
barter_auth/models/profiles.py
barter_auth/models/users.py
barter_auth/permissions/__init__.py
barter_auth/permissions/constants.py
barter_auth-0.3.43.dist-info/LICENSE
barter_auth-0.3.43.dist-info/METADATA
barter_auth-0.3.43.dist-info/WHEEL
barter_auth-0.3.43.dist-info/top_level.txt
barter_auth-0.3.43.dist-info/RECORD
