Metadata-Version: 2.1
Name: barter-auth
Version: 0.3.43
Summary: Barter authentication package
Home-page: https://github.com/kabilovtoha/barter_auth
Author: akatoha
Author-email: kabilov2011@gmail.com
License: BSD
Classifier: Environment :: Web Environment
Classifier: Framework :: Django
Classifier: Intended Audience :: Developers
Classifier: License :: OSI Approved :: BSD License
Classifier: Operating System :: OS Independent
Classifier: Programming Language :: Python :: 3.11
Classifier: Topic :: Software Development :: Libraries :: Python Modules
License-File: LICENSE
Requires-Dist: Django >=3.2
Requires-Dist: six >=1.15.0
Requires-Dist: pydantic-settings >=2.1.0
Requires-Dist: redis >=4.6.0
Requires-Dist: pydantic >=1.10.9
Requires-Dist: httpx >=0.24.1
Requires-Dist: factory-boy >=3.2.1
Requires-Dist: faker >=18.11.1
